mcp_database_server/__init__.py
mcp_database_server/cli.py
mcp_database_server/connection_manager.py
mcp_database_server/database_factory.py
mcp_database_server/dsn_parser.py
mcp_database_server/server.py
mcp_database_server/types.py
mcp_database_server/databases/__init__.py
mcp_database_server/databases/base.py
mcp_database_server/databases/mongodb.py
mcp_database_server/databases/mssql.py
mcp_database_server/databases/mysql.py
mcp_database_server/databases/postgresql.py
mcp_database_server/databases/redis.py
mcp_database_server/databases/sqlite.py
mcp_universal_database_server-0.3.5.dist-info/METADATA
mcp_universal_database_server-0.3.5.dist-info/WHEEL
mcp_universal_database_server-0.3.5.dist-info/entry_points.txt
mcp_universal_database_server-0.3.5.dist-info/licenses/LICENSE
mcp_universal_database_server-0.3.5.dist-info/RECORD
