Metadata-Version: 2.4
Name: mcp-universal-database-server
Version: 0.3.5
Summary: Universal MCP server for multiple database connections and operations
Project-URL: Homepage, https://github.com/adarshbhayani/mcp-database-server
Project-URL: Repository, https://github.com/adarshbhayani/mcp-database-server
Project-URL: Documentation, https://github.com/adarshbhayani/mcp-database-server#readme
Project-URL: Issues, https://github.com/adarshbhayani/mcp-database-server/issues
Author-email: Adarsh Bhayani <adarsh.bhayani@simformsolutions.com>
License: MIT
License-File: LICENSE
Keywords: database,mcp,mongodb,mysql,nosql,postgresql,server,sql,sqlite
Classifier: Development Status :: 4 - Beta
Classifier: Intended Audience :: Developers
Classifier: License :: OSI Approved :: MIT License
Classifier: Programming Language :: Python :: 3
Classifier: Programming Language :: Python :: 3.10
Classifier: Programming Language :: Python :: 3.11
Classifier: Programming Language :: Python :: 3.12
Classifier: Topic :: Database
Classifier: Topic :: Software Development :: Libraries :: Python Modules
Requires-Python: >=3.10
Requires-Dist: aiomysql>=0.2.0
Requires-Dist: aioodbc>=0.4.0
Requires-Dist: aiosqlite>=0.20.0
Requires-Dist: asyncio-mqtt>=0.16.0
Requires-Dist: asyncpg>=0.29.0
Requires-Dist: azure-cosmos>=4.5.0
Requires-Dist: boto3>=1.34.0
Requires-Dist: cassandra-driver>=3.29.0
Requires-Dist: click>=8.1.0
Requires-Dist: cryptography>=41.0.0
Requires-Dist: google-cloud-firestore>=2.13.0
Requires-Dist: mcp>=1.0.0
Requires-Dist: motor>=3.3.0
Requires-Dist: pydantic>=2.0.0
Requires-Dist: pyodbc>=4.0.0
Requires-Dist: python-dotenv>=1.0.0
Requires-Dist: redis[hiredis]>=5.0.0
Requires-Dist: rich>=13.0.0
Requires-Dist: sqlalchemy[asyncio]>=2.0.0
Requires-Dist: typer>=0.9.0
Provides-Extra: dev
Requires-Dist: black>=23.0.0; extra == 'dev'
Requires-Dist: mypy>=1.6.0; extra == 'dev'
Requires-Dist: pre-commit>=3.5.0; extra == 'dev'
Requires-Dist: pytest-asyncio>=0.21.0; extra == 'dev'
Requires-Dist: pytest>=7.0.0; extra == 'dev'
Requires-Dist: ruff>=0.1.0; extra == 'dev'
